hpexome/HPexome.scala
hpexome/Queue.jar
hpexome/__init__.py
hpexome/hpexome.py
HPexome-1.2.1.dist-info/LICENSE
HPexome-1.2.1.dist-info/METADATA
HPexome-1.2.1.dist-info/WHEEL
HPexome-1.2.1.dist-info/entry_points.txt
HPexome-1.2.1.dist-info/top_level.txt
HPexome-1.2.1.dist-info/RECORD
