Metadata-Version: 2.1
Name: HPexome
Version: 1.2.1
Summary: An automated tool for processing whole-exome sequencing data
Home-page: http://bcblab.org/hpexome
Author: Welliton Souza
Author-email: well309@gmail.com
License: UNKNOWN
Project-URL: Source Code, https://github.com/labbcb/hpexome
Project-URL: Bug Tracker, https://github.com/labbcb/hpexome/issues
Platform: UNKNOWN
Classifier: Programming Language :: Python :: 3
Requires-Dist: Click
